MANIFEST.in
README.rst
setup.py
pkcs1/__init__.py
pkcs1/defaults.py
pkcs1/eme_pkcs1_v15.py
pkcs1/emsa_pkcs1_v15.py
pkcs1/emsa_pss.py
pkcs1/exceptions.py
pkcs1/keys.py
pkcs1/mgf.py
pkcs1/primes.py
pkcs1/primitives.py
pkcs1/rsaes_oaep.py
pkcs1/rsaes_pkcs1_v15.py
pkcs1/rsassa_pkcs1_v15.py
pkcs1/rsassa_pss.py
pkcs1.egg-info/PKG-INFO
pkcs1.egg-info/SOURCES.txt
pkcs1.egg-info/dependency_links.txt
pkcs1.egg-info/top_level.txt
ref/rfc3447.txt.gz
ref/rfc5958.txt
tests/data.py
tests/rsaes_oaep.py
tests/test_emsa_pss.py
tests/test_naive_encryption.py
tests/test_rsaes_oaep.py
tests/test_rsaes_pkcs1_v15.py
tests/test_rsassa_pkcs1_v15.py
tests/test_rsassa_pss.py
tests/data/oaep-int.txt
tests/data/oaep-vect.txt
tests/data/pkcs1v15crypt-vectors.txt
tests/data/pkcs1v15sign-vectors.txt
tests/data/pss-int.txt
tests/data/pss-vect.txt
tests/data/readme.txt