Metadata-Version: 1.0
Name: pkcs1
Version: 0.9.6
Summary: Python implementation of the RFC3447 or PKCS #1 version 2.0
Home-page: https://github.com/bdauvergne/python-pkcs1
Author: Benjamin Dauvergne
Author-email: bdauvergne@entrouvert.com
License: MIT
Platform: UNKNOWN
